mosaic_it.py
mosaic_it-0.0.2.dist-info/METADATA
mosaic_it-0.0.2.dist-info/WHEEL
mosaic_it-0.0.2.dist-info/entry_points.txt
mosaic_it-0.0.2.dist-info/licenses/LICENSE
mosaic_it-0.0.2.dist-info/RECORD
