Metadata-Version: 2.4
Name: mosaic-it
Version: 0.0.2
Summary: A CLI tool to launch a OpenCV view to add a mosaic to the image.
Project-URL: Homepage, https://github.com/OldVincent/MosaicIt
Project-URL: Issues, https://github.com/OldVincent/MosaicIt/issues
Author-email: OldVincent <jia@jsk.imi.i.u-tokyo.ac.jp>
License-File: LICENSE
Classifier: License :: OSI Approved :: MIT License
Classifier: Operating System :: OS Independent
Classifier: Programming Language :: Python :: 3
Requires-Python: >=3.8
Requires-Dist: opencv-python
Requires-Dist: typer
